dfcleanser/__init__.py
dfcleanser/common/__init__.py
dfcleanser/common/cfg.py
dfcleanser/common/common_utils.py
dfcleanser/common/help_utils.py
dfcleanser/common/html_widgets.py
dfcleanser-1.0.0.dist-info/LICENSE.md
dfcleanser-1.0.0.dist-info/METADATA
dfcleanser-1.0.0.dist-info/WHEEL
dfcleanser-1.0.0.dist-info/top_level.txt
dfcleanser-1.0.0.dist-info/RECORD
