Metadata-Version: 2.1
Name: dfcleanser
Version: 1.0.0
Summary: A Jupyter notebook extension for dataframe cleansing
Home-page: https://github.com/RickKrasinski/dfcleanser
Author: Rick Krasinski
Author-email: rickmkrasinski@gmail.com
Classifier: Programming Language :: Python :: 3
Classifier: License :: Free for non-commercial use
Classifier: Operating System :: OS Independent
License-File: LICENSE.md
Requires-Dist: jupyter ==1
